LICENSE
MANIFEST.in
README.rst
requirements.txt
setup.py
lib/topology_lib_ping/__init__.py
lib/topology_lib_ping/library.py
lib/topology_lib_ping.egg-info/PKG-INFO
lib/topology_lib_ping.egg-info/SOURCES.txt
lib/topology_lib_ping.egg-info/dependency_links.txt
lib/topology_lib_ping.egg-info/entry_points.txt
lib/topology_lib_ping.egg-info/pbr.json
lib/topology_lib_ping.egg-info/requires.txt
lib/topology_lib_ping.egg-info/top_level.txt