Metadata-Version: 1.1
Name: topology-lib-ping
Version: 0.1.0
Summary: Linux ping command Communication Library for the Topology Network Framework.
Home-page: https://github.com/HPENetworking/topology_lib_ping/tree/master/doc
Author: Hewlett Packard Enterprise Development LP
Author-email: hpe-networking@lists.hp.com
License: UNKNOWN
Keywords: topology_lib_ping
Platform: UNKNOWN
Classifier: Development Status :: 3 - Alpha
Classifier: Intended Audience :: Developers
Classifier: License :: OSI Approved :: Apache Software License
Classifier: Natural Language :: English
Classifier: Operating System :: POSIX :: Linux
Classifier: Programming Language :: Python :: 2
Classifier: Programming Language :: Python :: 2.7
Classifier: Programming Language :: Python :: 3
Classifier: Programming Language :: Python :: 3.4
